gitversion/version.py
gitversion/__init__.py
gitversion-2.1.3.dist-info/WHEEL
gitversion-2.1.3.dist-info/top_level.txt
gitversion-2.1.3.dist-info/RECORD
gitversion-2.1.3.dist-info/DESCRIPTION.rst
gitversion-2.1.3.dist-info/pydist.json
gitversion-2.1.3.dist-info/METADATA
